[
  {
    "date": "2026-03-24 08:21",
    "performance": [
      {
        "ticker": "S-Oil",
        "change": -5.19
      },
      {
        "ticker": "Exxon Mobil",
        "change": 0.91
      },
      {
        "ticker": "Tesla",
        "change": 3.5
      }
    ],
    "predictions": [
      "삼성전자",
      "마이크론",
      "테슬라"
    ]
  },
  {
    "date": "2026-03-25 08:20",
    "performance": [
      {
        "ticker": "삼성전자",
        "change": 1.83
      },
      {
        "ticker": "마이크론",
        "change": -2.18
      },
      {
        "ticker": "테슬라",
        "change": 0.57
      }
    ],
    "predictions": [
      "SK하이닉스",
      "셀트리온",
      "Exxon Mobil"
    ]
  },
  {
    "date": "2026-03-26 08:22",
    "performance": [
      {
        "ticker": "SK하이닉스",
        "change": 0.91
      },
      {
        "ticker": "셀트리온",
        "change": 1.95
      },
      {
        "ticker": "Exxon Mobil",
        "change": -1.28
      }
    ],
    "predictions": [
      "알테오젠",
      "NVIDIA",
      "Microsoft"
    ]
  },
  {
    "date": "2026-03-27 08:19",
    "performance": [
      {
        "ticker": "알테오젠",
        "change": 6.28
      },
      {
        "ticker": "NVIDIA",
        "change": -4.16
      },
      {
        "ticker": "Microsoft",
        "change": -1.37
      }
    ],
    "predictions": [
      "알테오젠",
      "엑손모빌",
      "제이피모건 체이스"
    ]
  },
  {
    "date": "2026-03-28 08:21",
    "performance": [
      {
        "ticker": "알테오젠",
        "change": 0.0
      },
      {
        "ticker": "엑손모빌",
        "change": 3.36
      },
      {
        "ticker": "제이피모건 체이스",
        "change": -3.02
      }
    ],
    "predictions": [
      "한화솔루션",
      "엑손모빌",
      "JP모건 체이스"
    ]
  },
  {
    "date": "2026-03-29 08:19",
    "performance": [
      {
        "ticker": "한화솔루션",
        "change": 0.0
      },
      {
        "ticker": "엑손모빌",
        "change": 3.36
      },
      {
        "ticker": "JP모건 체이스",
        "change": -3.02
      }
    ],
    "predictions": [
      "삼성전자",
      "마이크로소프트",
      "TSMC"
    ]
  },
  {
    "date": "2026-03-30 08:21",
    "performance": [
      {
        "ticker": "삼성전자",
        "change": 0.0
      },
      {
        "ticker": "마이크로소프트",
        "change": -2.51
      },
      {
        "ticker": "TSMC",
        "change": 0.19
      }
    ],
    "predictions": [
      "삼성전자",
      "엑손모빌",
      "코카콜라"
    ]
  },
  {
    "date": "2026-03-31 08:25",
    "performance": [
      {
        "ticker": "삼성전자",
        "change": -2.11
      },
      {
        "ticker": "엑손모빌",
        "change": 0.28
      },
      {
        "ticker": "코카콜라",
        "change": 0.74
      }
    ],
    "predictions": [
      "S-Oil",
      "Exxon Mobil",
      "Chevron"
    ]
  },
  {
    "date": "2026-04-01 08:22",
    "performance": [
      {
        "ticker": "S-Oil",
        "change": -4.36
      },
      {
        "ticker": "Exxon Mobil",
        "change": -1.06
      },
      {
        "ticker": "Chevron",
        "change": -1.81
      }
    ],
    "predictions": [
      "삼성바이오로직스",
      "NVIDIA",
      "Nike"
    ]
  },
  {
    "date": "2026-04-02 08:26",
    "performance": [
      {
        "ticker": "삼성바이오로직스",
        "change": 4.52
      },
      {
        "ticker": "NVIDIA",
        "change": 0.77
      },
      {
        "ticker": "Nike",
        "change": -15.51
      }
    ],
    "predictions": [
      "롯데바이오로직스(관련주: 롯데지주)",
      "Eli Lilly",
      "Oracle"
    ]
  },
  {
    "date": "2026-04-04 08:23",
    "performance": [
      {
        "ticker": "롯데바이오로직스(관련주: 롯데지주)",
        "change": 0.37
      },
      {
        "ticker": "Eli Lilly",
        "change": -1.98
      },
      {
        "ticker": "Oracle",
        "change": 0.79
      }
    ],
    "predictions": [
      "한화에어로스페이스",
      "일라이 릴리",
      "엑손 모빌"
    ]
  },
  {
    "date": "2026-04-05 08:19",
    "performance": [
      {
        "ticker": "한화에어로스페이스",
        "change": 2.26
      },
      {
        "ticker": "일라이 릴리",
        "change": -1.98
      },
      {
        "ticker": "엑손 모빌",
        "change": -0.06
      }
    ],
    "predictions": [
      "삼성전자",
      "엑손모빌",
      "록히드마틴"
    ]
  },
  {
    "date": "2026-04-06 08:22",
    "performance": [
      {
        "ticker": "삼성전자",
        "change": 4.37
      },
      {
        "ticker": "엑손모빌",
        "change": -0.06
      },
      {
        "ticker": "록히드마틴",
        "change": 0.83
      }
    ],
    "predictions": [
      "현대중공업",
      "Exxon Mobil",
      "Lockheed Martin"
    ]
  },
  {
    "date": "2026-04-07 08:25",
    "performance": [
      {
        "ticker": "현대중공업",
        "change": -1.77
      },
      {
        "ticker": "Exxon Mobil",
        "change": 1.67
      },
      {
        "ticker": "Lockheed Martin",
        "change": 2.43
      }
    ],
    "predictions": [
      "삼성전자",
      "엔비디아",
      "유나이티드헬스 그룹"
    ]
  },
  {
    "date": "2026-04-08 08:27",
    "performance": [
      {
        "ticker": "삼성전자",
        "change": 1.76
      },
      {
        "ticker": "엔비디아",
        "change": 0.26
      },
      {
        "ticker": "유나이티드헬스 그룹",
        "change": 9.37
      }
    ],
    "predictions": [
      "삼성전자",
      "유나이티드헬스 그룹",
      "애플"
    ]
  },
  {
    "date": "2026-04-09 08:28",
    "performance": [
      {
        "ticker": "삼성전자",
        "change": 7.12
      },
      {
        "ticker": "유나이티드헬스 그룹",
        "change": -0.57
      },
      {
        "ticker": "애플",
        "change": 2.13
      }
    ],
    "predictions": [
      "삼성전자",
      "메타 플랫폼스",
      "GE 에어로스페이스"
    ]
  },
  {
    "date": "2026-04-10 08:29",
    "performance": [
      {
        "ticker": "삼성전자",
        "change": -3.09
      },
      {
        "ticker": "메타 플랫폼스",
        "change": 2.61
      },
      {
        "ticker": "GE 에어로스페이스",
        "change": 1.61
      }
    ],
    "predictions": [
      "한국항공우주",
      "Meta Platforms",
      "Palantir Technologies"
    ]
  },
  {
    "date": "2026-04-11 08:24",
    "performance": [
      {
        "ticker": "한국항공우주",
        "change": 0.0
      },
      {
        "ticker": "Meta Platforms",
        "change": 0.23
      },
      {
        "ticker": "Palantir Technologies",
        "change": -1.86
      }
    ],
    "predictions": [
      "삼성전자",
      "서비스나우",
      "SK하이닉스"
    ]
  },
  {
    "date": "2026-04-12 08:21",
    "performance": [
      {
        "ticker": "삼성전자",
        "change": 0.98
      },
      {
        "ticker": "서비스나우",
        "change": -7.58
      },
      {
        "ticker": "SK하이닉스",
        "change": 2.91
      }
    ],
    "predictions": [
      "현대차",
      "Exxon Mobil",
      "Alphabet"
    ]
  },
  {
    "date": "2026-04-13 08:23",
    "performance": [
      {
        "ticker": "현대차",
        "change": 0.0
      },
      {
        "ticker": "Exxon Mobil",
        "change": -1.63
      },
      {
        "ticker": "Alphabet",
        "change": -0.39
      }
    ],
    "predictions": [
      "삼성전자",
      "LIG넥스원",
      "Alphabet"
    ]
  },
  {
    "date": "2026-04-14 08:33",
    "performance": [
      {
        "ticker": "삼성전자",
        "change": -2.43
      },
      {
        "ticker": "LIG넥스원",
        "change": 1.95
      },
      {
        "ticker": "Alphabet",
        "change": 1.28
      }
    ],
    "predictions": [
      "LS ELECTRIC",
      "Amazon",
      "Dell Technologies"
    ]
  },
  {
    "date": "2026-04-15 08:33",
    "performance": [
      {
        "ticker": "LS ELECTRIC",
        "change": 3.57
      },
      {
        "ticker": "Amazon",
        "change": 3.81
      },
      {
        "ticker": "Dell Technologies",
        "change": -2.78
      }
    ],
    "predictions": [
      "SK하이닉스",
      "Amazon",
      "JPMorgan Chase"
    ]
  },
  {
    "date": "2026-04-16 08:32",
    "performance": [
      {
        "ticker": "SK하이닉스",
        "change": 2.99
      },
      {
        "ticker": "Amazon",
        "change": -0.21
      },
      {
        "ticker": "JPMorgan Chase",
        "change": -1.67
      }
    ],
    "predictions": [
      "삼성전자",
      "스타벅스",
      "스냅"
    ]
  },
  {
    "date": "2026-04-17 08:30",
    "performance": [
      {
        "ticker": "삼성전자",
        "change": 3.08
      },
      {
        "ticker": "스타벅스",
        "change": 0.02
      },
      {
        "ticker": "스냅",
        "change": -0.33
      }
    ],
    "predictions": [
      "삼성전자",
      "TSMC",
      "일라이 릴리"
    ]
  },
  {
    "date": "2026-04-18 08:29",
    "performance": [
      {
        "ticker": "삼성전자",
        "change": -0.69
      },
      {
        "ticker": "TSMC",
        "change": 1.97
      },
      {
        "ticker": "일라이 릴리",
        "change": 2.55
      }
    ],
    "predictions": [
      "삼성전자",
      "Cerebras Systems",
      "Eli Lilly and Company"
    ]
  },
  {
    "date": "2026-04-19 08:24",
    "performance": [
      {
        "ticker": "삼성전자",
        "change": -0.69
      },
      {
        "ticker": "Eli Lilly and Company",
        "change": 2.55
      }
    ],
    "predictions": [
      "삼성전자",
      "테슬라",
      "마이크로소프트"
    ]
  },
  {
    "date": "2026-04-20 08:25",
    "performance": [
      {
        "ticker": "삼성전자",
        "change": -0.69
      },
      {
        "ticker": "테슬라",
        "change": 3.01
      },
      {
        "ticker": "마이크로소프트",
        "change": 0.6
      }
    ],
    "predictions": [
      "SK하이닉스",
      "NVIDIA",
      "Advanced Micro Devices"
    ]
  },
  {
    "date": "2026-04-21 08:32",
    "performance": [
      {
        "ticker": "SK하이닉스",
        "change": 3.37
      },
      {
        "ticker": "NVIDIA",
        "change": 0.19
      },
      {
        "ticker": "Advanced Micro Devices",
        "change": -1.24
      }
    ],
    "predictions": [
      "POSCO홀딩스",
      "엑슨모빌",
      "알파벳"
    ]
  },
  {
    "date": "2026-04-22 08:25",
    "performance": [
      {
        "ticker": "POSCO홀딩스",
        "change": 8.22
      },
      {
        "ticker": "엑슨모빌",
        "change": 0.46
      },
      {
        "ticker": "알파벳",
        "change": -1.52
      }
    ],
    "predictions": [
      "유한양행",
      "Amazon",
      "Eli Lilly"
    ]
  },
  {
    "date": "2026-04-23 08:37",
    "performance": [
      {
        "ticker": "유한양행",
        "change": -1.45
      },
      {
        "ticker": "Amazon",
        "change": 2.18
      },
      {
        "ticker": "Eli Lilly",
        "change": 2.04
      }
    ],
    "predictions": [
      "SK하이닉스",
      "LIG넥스원",
      "Tesla"
    ]
  }
]